MASSA_Algorithm/MASSA.py
MASSA_Algorithm/MASSAargs.py
MASSA_Algorithm/MASSAcluster.py
MASSA_Algorithm/MASSAdescriptors.py
MASSA_Algorithm/MASSAextraction.py
MASSA_Algorithm/MASSAlogos.py
MASSA_Algorithm/MASSAmoloutput.py
MASSA_Algorithm/MASSAod.py
MASSA_Algorithm/MASSAopen_files.py
MASSA_Algorithm/MASSApreparation.py
MASSA_Algorithm/MASSAsplit.py
MASSA_Algorithm/__init__.py
MASSA_Algorithm/pyMASSA.py
massa_algorithm-2.2.0.dist-info/licenses/LICENSE
massa_algorithm-2.2.0.dist-info/METADATA
massa_algorithm-2.2.0.dist-info/WHEEL
massa_algorithm-2.2.0.dist-info/entry_points.txt
massa_algorithm-2.2.0.dist-info/top_level.txt
massa_algorithm-2.2.0.dist-info/RECORD
