Metadata-Version: 2.4
Name: MASSA_Algorithm
Version: 2.2.0
Summary: MASSA Algorithm is a Python package to separate data sets of molecules into training and test sets, considering the diversity of structural, physicochemical and biological characteristics of these molecules.
Home-page: https://github.com/gcverissimo/MASSA_Algorithm
Author: Gabriel Corrêa Veríssimo
Author-email: gcverissimo@outlook.com
License: AGPLv3
Keywords: chemoinformatics,training,test,training-test,dataset preparation,data set preparation,rdkit
Classifier: Programming Language :: Python :: 3
Classifier: Programming Language :: Python :: 3.8
Classifier: Programming Language :: Python :: 3.9
Classifier: Programming Language :: Python :: 3.10
Classifier: Programming Language :: Python :: 3.11
Classifier: License :: OSI Approved :: GNU Affero General Public License v3
Classifier: Operating System :: OS Independent
Classifier: Topic :: Scientific/Engineering :: Chemistry
Requires-Python: >=3.8
License-File: LICENSE
Requires-Dist: numpy
Requires-Dist: rdkit
Requires-Dist: pandas
Requires-Dist: matplotlib>=3.2
Requires-Dist: scipy>=1.6
Requires-Dist: scikit-learn>0.24
Requires-Dist: kmodes>=0.10
Dynamic: author
Dynamic: author-email
Dynamic: classifier
Dynamic: description
Dynamic: description-content-type
Dynamic: home-page
Dynamic: keywords
Dynamic: license
Dynamic: license-file
Dynamic: requires-dist
Dynamic: requires-python
Dynamic: summary
